tidal_dl_ng/__init__.py
tidal_dl_ng/api.py
tidal_dl_ng/cache.py
tidal_dl_ng/cli.py
tidal_dl_ng/config.py
tidal_dl_ng/constants.py
tidal_dl_ng/dialog.py
tidal_dl_ng/dialog_history.py
tidal_dl_ng/download.py
tidal_dl_ng/gui/__init__.py
tidal_dl_ng/gui/activate.py
tidal_dl_ng/gui/context_menus.py
tidal_dl_ng/gui/covers.py
tidal_dl_ng/gui/dialog_playlist_manager.py
tidal_dl_ng/gui/downloads.py
tidal_dl_ng/gui/history.py
tidal_dl_ng/gui/initialization.py
tidal_dl_ng/gui/main_window.py
tidal_dl_ng/gui/playlist.py
tidal_dl_ng/gui/playlist_membership.py
tidal_dl_ng/gui/playlist_membership_mixin.py
tidal_dl_ng/gui/progress.py
tidal_dl_ng/gui/queue.py
tidal_dl_ng/gui/search.py
tidal_dl_ng/gui/signals.py
tidal_dl_ng/gui/tidal_session.py
tidal_dl_ng/gui/track_extras.py
tidal_dl_ng/gui/trees_results.py
tidal_dl_ng/gui/ui_helpers.py
tidal_dl_ng/gui/updates.py
tidal_dl_ng/gui.py
tidal_dl_ng/helper/__init__.py
tidal_dl_ng/helper/decorator.py
tidal_dl_ng/helper/decryption.py
tidal_dl_ng/helper/exceptions.py
tidal_dl_ng/helper/gui.py
tidal_dl_ng/helper/hover_manager.py
tidal_dl_ng/helper/metadata_utils.py
tidal_dl_ng/helper/path.py
tidal_dl_ng/helper/playlist_api.py
tidal_dl_ng/helper/tidal.py
tidal_dl_ng/helper/wrapper.py
tidal_dl_ng/history.py
tidal_dl_ng/logger.py
tidal_dl_ng/metadata.py
tidal_dl_ng/model/__init__.py
tidal_dl_ng/model/cfg.py
tidal_dl_ng/model/downloader.py
tidal_dl_ng/model/gui_data.py
tidal_dl_ng/model/meta.py
tidal_dl_ng/ui/__init__.py
tidal_dl_ng/ui/default_album_image.png
tidal_dl_ng/ui/dialog_history.py
tidal_dl_ng/ui/dialog_history.ui
tidal_dl_ng/ui/dialog_login.py
tidal_dl_ng/ui/dialog_login.ui
tidal_dl_ng/ui/dialog_playlist_manager.py
tidal_dl_ng/ui/dialog_playlist_manager.ui
tidal_dl_ng/ui/dialog_settings.py
tidal_dl_ng/ui/dialog_settings.ui
tidal_dl_ng/ui/dialog_version.py
tidal_dl_ng/ui/dialog_version.ui
tidal_dl_ng/ui/dummy_register.py
tidal_dl_ng/ui/dummy_wiggly.py
tidal_dl_ng/ui/icon.icns
tidal_dl_ng/ui/icon.ico
tidal_dl_ng/ui/icon16.png
tidal_dl_ng_for_dj-0.32.0.dist-info/METADATA
tidal_dl_ng_for_dj-0.32.0.dist-info/WHEEL
tidal_dl_ng_for_dj-0.32.0.dist-info/entry_points.txt
tidal_dl_ng_for_dj-0.32.0.dist-info/licenses/LICENSE
tidal_dl_ng_for_dj-0.32.0.dist-info/RECORD
