Metadata-Version: 2.4
Name: tidal-dl-ng-for-dj
Version: 0.32.0
Summary: TIDAL Media Downloader Next Generation!
License-Expression: AGPL-3.0-only
License-File: LICENSE
Author: Warry
Author-email: <warry@exemple.com>
Requires-Python: >=3.12,<3.14
Classifier: Development Status :: 4 - Beta
Classifier: Intended Audience :: Developers
Classifier: Programming Language :: Python :: 3
Classifier: Programming Language :: Python :: 3.12
Classifier: Programming Language :: Python :: 3.13
Provides-Extra: gui
Requires-Dist: ansi2html (>=1.9.2,<2.0.0)
Requires-Dist: coloredlogs (>=15.0.1,<16.0.0)
Requires-Dist: dataclasses-json (>=0.6.7,<0.7.0)
Requires-Dist: m3u8 (>=6.0.0,<7.0.0)
Requires-Dist: mutagen (>=1.47.0,<2.0.0)
Requires-Dist: pathvalidate (>=3.3.1,<4.0.0)
Requires-Dist: pycryptodome (>=3.23.0,<4.0.0)
Requires-Dist: pyqtdarktheme-fork ; extra == "gui"
Requires-Dist: pyside6 ; extra == "gui"
Requires-Dist: python-ffmpeg (>=2.0.12,<3.0.0)
Requires-Dist: requests (>=2.32.5,<2.33.0)
Requires-Dist: rich (>=14.2.0,<15.0.0)
Requires-Dist: tidalapi (>=0.8.8,<0.9.0)
Requires-Dist: toml (>=0.10.2,<0.11.0)
Requires-Dist: typer (>=0.20.0,<0.21.0)
Project-URL: Documentation, https://FunWarry.github.io/tidal-dl-ng-For-DJ/
Project-URL: Repository, https://github.com/FunWarry/tidal-dl-ng-For-DJ
